zefram/__init__.py
zefram/frameworks.db
zefram/zefram.py
zefram-0.1.3.dist-info/LICENSE.rst
zefram-0.1.3.dist-info/WHEEL
zefram-0.1.3.dist-info/METADATA
zefram-0.1.3.dist-info/RECORD
