Metadata-Version: 2.1
Name: zefram
Version: 0.1.3
Summary: Database of zeolite framework characteristics
Home-page: https://github.com/lmmentel/zefram
License: MIT
Author: Lukasz Mentel
Author-email: lmmentel@gmail.com
Maintainer: Lukasz Mentel
Maintainer-email: lmmentel@gmail.com
Requires-Python: >=3.8,<3.11
Classifier: License :: OSI Approved :: MIT License
Classifier: Programming Language :: Python :: 3
Classifier: Programming Language :: Python :: 3.8
Classifier: Programming Language :: Python :: 3.9
Requires-Dist: SQLAlchemy (>=1.4.22,<2.0.0)
Requires-Dist: numpy (>=1.21.2,<2.0.0)
Project-URL: Repository, https://github.com/lmmentel/zefram
